nadtcp/__init__.py
nadtcp2-1.0.0.dist-info/LICENSE
nadtcp2-1.0.0.dist-info/METADATA
nadtcp2-1.0.0.dist-info/WHEEL
nadtcp2-1.0.0.dist-info/top_level.txt
nadtcp2-1.0.0.dist-info/RECORD
