Metadata-Version: 2.1
Name: nadtcp2
Version: 1.0.0
Summary: Library for TCP/IP enabled NAD amplifiers. Currently only the C338 is supported.
Author-email: IAmRGroot <github@rgroot.nl>
License: MIT License        
Project-URL: Homepage, https://github.com/realpython/reader
Keywords: nad,c338,nadtcp
Classifier: License :: OSI Approved :: MIT License
Classifier: Programming Language :: Python
Classifier: Programming Language :: Python :: 3
Requires-Python: >=3.10
License-File: LICENSE
Provides-Extra: dev
Requires-Dist: build ; extra == 'dev'
Requires-Dist: twine ; extra == 'dev'
Requires-Dist: pip-tools ; extra == 'dev'
